jarvis/__init__.py
jarvis/main.py
jarvis/_preexec/keywords_handler.py
jarvis/api/fast.py
jarvis/api/server.py
jarvis/api/modals/authenticator.py
jarvis/api/modals/models.py
jarvis/api/modals/settings.py
jarvis/api/routers/basics.py
jarvis/api/routers/fileio.py
jarvis/api/routers/helper.py
jarvis/api/routers/investment.py
jarvis/api/routers/offline.py
jarvis/api/routers/speech_synthesis.py
jarvis/api/routers/stock_monitor.py
jarvis/api/routers/surveillance.py
jarvis/api/squire/discover.py
jarvis/api/squire/favicon.ico
jarvis/api/squire/logger.py
jarvis/api/squire/scheduler.py
jarvis/api/squire/stockmonitor_squire.py
jarvis/api/squire/surveillance_squire.py
jarvis/api/squire/timeout_otp.py
jarvis/api/triggers/stock_monitor.py
jarvis/api/triggers/stock_report.py
jarvis/executors/alarm.py
jarvis/executors/automation.py
jarvis/executors/background_task.py
jarvis/executors/car.py
jarvis/executors/comm_squire.py
jarvis/executors/commander.py
jarvis/executors/communicator.py
jarvis/executors/conditions.py
jarvis/executors/connection.py
jarvis/executors/controls.py
jarvis/executors/crontab.py
jarvis/executors/date_time.py
jarvis/executors/display_functions.py
jarvis/executors/face.py
jarvis/executors/files.py
jarvis/executors/github.py
jarvis/executors/guard.py
jarvis/executors/internet.py
jarvis/executors/ios_functions.py
jarvis/executors/lights.py
jarvis/executors/lights_squire.py
jarvis/executors/listener_controls.py
jarvis/executors/location.py
jarvis/executors/myq_controller.py
jarvis/executors/offline.py
jarvis/executors/others.py
jarvis/executors/port_handler.py
jarvis/executors/processor.py
jarvis/executors/remind.py
jarvis/executors/robinhood.py
jarvis/executors/simulator.py
jarvis/executors/system.py
jarvis/executors/telegram.py
jarvis/executors/todo_list.py
jarvis/executors/tv.py
jarvis/executors/tv_controls.py
jarvis/executors/unconditional.py
jarvis/executors/volume.py
jarvis/executors/vpn_server.py
jarvis/executors/weather.py
jarvis/executors/wiki.py
jarvis_ironman-7.2.2.dist-info/LICENSE
jarvis_ironman-7.2.2.dist-info/METADATA
jarvis_ironman-7.2.2.dist-info/WHEEL
jarvis_ironman-7.2.2.dist-info/top_level.txt
jarvis_ironman-7.2.2.dist-info/RECORD
