Metadata-Version: 2.1
Name: jarvis-ironman
Version: 7.2.2
Summary: Natural Language User Interface
Author-email: Vignesh Sivanandha Rao <svignesh1793@gmail.com>
License: MIT License
Project-URL: Homepage, https://github.com/thevickypedia/Jarvis
Project-URL: Docs, https://thevickypedia.github.io/Jarvis
Project-URL: Demo, https://vigneshrao.com/Jarvis/Jarvis_Demo.mp4
Project-URL: Source, https://github.com/thevickypedia/Jarvis
Project-URL: Bug Tracker, https://github.com/thevickypedia/Jarvis/issues
Project-URL: Release Notes, https://github.com/thevickypedia/Jarvis/blob/master/release_notes.rst
Keywords: python,home-automation,natural-language-processing,text-to-speech,speech-recognition,jarvis,hotword-detection,virtual-assistant
Classifier: Development Status :: 5 - Production/Stable
Classifier: Intended Audience :: Information Technology
Classifier: Operating System :: MacOS :: MacOS X
Classifier: Operating System :: Microsoft :: Windows :: Windows 10
Classifier: Operating System :: POSIX :: Linux
Classifier: License :: OSI Approved :: MIT License
Classifier: Programming Language :: Python :: 3.8
Classifier: Programming Language :: Python :: 3.9
Classifier: Programming Language :: Python :: 3.10
Classifier: Programming Language :: Python :: 3.11
Classifier: Topic :: Multimedia :: Sound/Audio :: Speech
Classifier: Topic :: Scientific/Engineering :: Human Machine Interfaces
Classifier: Topic :: Scientific/Engineering :: Artificial Intelligence
Classifier: Topic :: Home Automation
Classifier: Topic :: Scientific/Engineering :: Image Recognition
Classifier: Topic :: System :: Hardware :: Universal Serial Bus (USB) :: Wireless Controller
Classifier: Topic :: Multimedia :: Sound/Audio :: Conversion
Classifier: Topic :: Software Development :: Libraries :: Python Modules
Classifier: Topic :: System :: Hardware :: Hardware Drivers
Classifier: Topic :: System :: Hardware :: Symmetric Multi-processing
Classifier: Topic :: System :: Hardware :: Universal Serial Bus (USB) :: Human Interface Device (HID)
Classifier: Framework :: FastAPI
Classifier: Framework :: Flake8
Classifier: Framework :: AsyncIO
Classifier: Framework :: Sphinx
Classifier: Framework :: aiohttp
Classifier: Natural Language :: English
Requires-Python: >=3.8
License-File: LICENSE
Requires-Dist: SpeechRecognition (==3.8.1)
Requires-Dist: wave (==0.0.2)
Requires-Dist: pyttsx3 (==2.90)
Requires-Dist: wikipedia (==1.4.0)
Requires-Dist: newsapi-python (==0.2.7)
Requires-Dist: pyrh (==2.0)
Requires-Dist: pytz (==2023.3)
Requires-Dist: timezonefinder (==6.2.0)
Requires-Dist: pyicloud (==1.0.0)
Requires-Dist: geopy (==2.3.0)
Requires-Dist: PyYAML (==6.0)
Requires-Dist: axju-jokes (==1.0.3)
Requires-Dist: inflect (==6.0.2)
Requires-Dist: pywebostv (==0.8.9)
Requires-Dist: speedtest-cli (==2.1.3)
Requires-Dist: holidays (==0.21.13)
Requires-Dist: randfacts (==0.20.1)
Requires-Dist: wolframalpha (==5.0.0)
Requires-Dist: fastapi (==0.95.0)
Requires-Dist: uvicorn (==0.21.1)
Requires-Dist: aiofiles (==23.1.0)
Requires-Dist: python-multipart (==0.0.6)
Requires-Dist: pydantic[email] (==1.10.7)
Requires-Dist: ics (==0.7.2)
Requires-Dist: Jinja2 (==3.1.2)
Requires-Dist: certifi (==2022.12.7)
Requires-Dist: googlehomepush (==0.1.0)
Requires-Dist: PyChromecast (==2.3.0)
Requires-Dist: psutil (==5.9.4)
Requires-Dist: pytest (==7.2.2)
Requires-Dist: bs4 (==0.0.1)
Requires-Dist: Pillow (==9.4.0)
Requires-Dist: packaging (==23.0)
Requires-Dist: numpy (==1.24.2)
Requires-Dist: SoundFile (==0.12.1)
Requires-Dist: deepdiff (==6.3.0)
Requires-Dist: pymyq (==3.1.6)
Requires-Dist: docker (==6.0.1)
Requires-Dist: websockets (==10.4)
Requires-Dist: PyJWT (==2.6.0)
Requires-Dist: webull (==0.6.1)
Requires-Dist: matplotlib (==3.7.1)
Requires-Dist: pandas (==1.5.3)
Requires-Dist: lxml (==4.9.2)
Requires-Dist: aiohttp (==3.8.4)
Requires-Dist: python-dateutil (==2.8.2)
Requires-Dist: requests (==2.28.2)
Requires-Dist: sounddevice (==0.4.6)
Requires-Dist: gmail-connector
Requires-Dist: vpn-server
Requires-Dist: pycontrols
Provides-Extra: dev
Requires-Dist: pytest ; extra == 'dev'
Requires-Dist: pre-commit ; extra == 'dev'
